{
    "@context": {
        "@version": 1.1,
        "@protected": true,
        "id": "@id",
        "schema": "https://schema.org/",
        "UpSkillMitraCredential": {
            "@id": "https://suraj-tekdi.github.io/vc-json-schema/json_files/udc-context.json#UpSkillMitraCredential",
            "@context": {
                "@version": 1.1,
                "id": "@id",
                "user-id": "schema:Text",
                "user-full-name": "schema:Text",
                "user-first-name": "schema:Text",
                "user-middle-name": "schema:Text",
                "user-last-name": "schema:Text",
                "user-phone-number": "schema:Text",
                "user-email": "schema:Text",
                "user-date-of-birth": "schema:Text",
                "user-gender": "schema:Text",
                "user-martial-status": "schema:Text",
                "user-state-code": "schema:Text",
                "user-district-code": "schema:Text",
                "user-education-detail-id": "schema:Text",
                "edu-class-degree-0": "schema:Text",
                "edu-div-grade-0": "schema:Text",
                "edu-qual-percentage": "schema:Text",
                "user-skilling-detail-Id": "schema:Text",
                "user-course-type": "schema:Text",
                "user-sector-code": "schema:Text",
                "edu-course-code": "schema:Text",
                "edu-qual-completion-year": "schema:Text",
                "user-exp-in-skill": "schema:Text",
                "user-exp-in-month": "schema:Text"
            }
        }
    }
}
